terminal_wrapped/__init__.py
terminal_wrapped/comments.py
terminal_wrapped/main.py
terminal_wrapped-0.4.0.dist-info/METADATA
terminal_wrapped-0.4.0.dist-info/WHEEL
terminal_wrapped-0.4.0.dist-info/entry_points.txt
terminal_wrapped-0.4.0.dist-info/RECORD
