Metadata-Version: 2.3
Name: terminal_wrapped
Version: 0.4.0
Summary: Add your description here
Project-URL: GitHub, https://github.com/raoulg/terminal_wrapped
Author-email: Raoul Grouls <Raoul.Grouls@han.nl>
Requires-Python: >=3.12
Requires-Dist: colorama>=0.4.6
